openchecks-0.2.0.dist-info/METADATA
openchecks-0.2.0.dist-info/WHEEL
openchecks.libs/libgcc_s-5b5488a6.so.1
openchecks/__init__.py
openchecks/__init__.pyi
openchecks/openchecks.cpython-39-arm-linux-gnueabihf.so
openchecks/py.typed
openchecks-0.2.0.dist-info/RECORD
